sonic/__init__.py
sonic/client.py
sonic_client-1.0.0.dist-info/LICENSE
sonic_client-1.0.0.dist-info/METADATA
sonic_client-1.0.0.dist-info/WHEEL
sonic_client-1.0.0.dist-info/top_level.txt
sonic_client-1.0.0.dist-info/RECORD
