Metadata-Version: 2.1
Name: sonic-client
Version: 1.0.0
Summary: python client for sonic search backend
Home-page: https://github.com/xmonader/python-sonic-client
Author: Ahmed T. Youssef
Author-email: xmonader@gmail.com
License: BSD 3-Clause License
Platform: UNKNOWN
Classifier: Development Status :: 3 - Alpha
Classifier: Environment :: Console
Classifier: Intended Audience :: Developers
Classifier: License :: OSI Approved :: Apache Software License
Classifier: Operating System :: OS Independent
Classifier: Programming Language :: Python
License-File: LICENSE
